{
  "comments": [
    {
      "id": 1,
      "comment": "hello world",
      "date": "4/2/2022",
      "time": "4:34:15 PM",
      "children": [
        {
          "comment": "hi world",
          "date": "4/2/2022",
          "time": "4:34:15 PM",
          "children": [
            {
              "comment": "hello kitty",
              "date": "4/2/2022",
              "time": "4:34:15 PM",
              "children": []
            }
          ]
        },
        {
          "comment": "hi jaccuzi",
          "date": "4/2/2022",
          "time": "5:34:15 PM",
          "children": []
        }
      ]
    },
    {
      "id": 2,
      "comment": "hello sam",
      "date": "4/2/2022",
      "time": "4:34:15 PM",
      "children": [
        {
          "comment": "hi world",
          "date": "4/2/2022",
          "time": "4:34:15 PM",
          "children": [
            {
              "comment": "hello kitty",
              "date": "4/2/2022",
              "time": "4:34:15 PM",
              "children": []
            }
          ]
        },
        {
          "comment": "hi jaccuzi",
          "date": "4/2/2022",
          "time": "5:34:15 PM",
          "children": []
        }
      ]
    },
    {
      "comment": "hellooooo.....",
      "date": "4/2/2022",
      "time": " 7:07:31 PM",
      "children": [],
      "id": 3
    },
    {
      "comment": "kanha",
      "date": "4/2/2022",
      "time": " 10:15:58 PM",
      "children": [],
      "id": 4
    }
  ]
}